{
  "feature_name": "project-initialize",
  "stage": "05_verify",
  "attempt": 1,
  "result_path": ".ai/runs/project-initialize/verification/05_verify_attempt1_20260527-103808.json",
  "latest_path": ".ai/runs/project-initialize/verification/latest.json",
  "started_at": "2026-05-27T10:38:08",
  "finished_at": "2026-05-27T10:38:08",
  "required": true,
  "passed": true,
  "status": "PASS",
  "commands": [
    {
      "name": "harness-python-compile",
      "command": [
        "python",
        "-m",
        "py_compile",
        ".ai\\harness.py",
        ".ai\\harness_fast.py",
        ".ai\\harness_standard.py",
        ".ai\\templates\\docx_helper.py"
      ],
      "cwd": ".",
      "timeout_seconds": 600,
      "returncode": 0,
      "elapsed_seconds": 0.13,
      "passed": true,
      "timed_out": false,
      "stdout": ".ai/runs/project-initialize/verification/05_verify_attempt1_harness-python-compile.out.txt",
      "stderr": ".ai/runs/project-initialize/verification/05_verify_attempt1_harness-python-compile.err.txt"
    },
    {
      "name": "git-diff-check",
      "command": [
        "git",
        "-c",
        "safe.directory=D:\\test\\vibe-coding-toolkit\\vibe-coding-toolkit",
        "diff",
        "--check"
      ],
      "cwd": ".",
      "timeout_seconds": 600,
      "returncode": 0,
      "elapsed_seconds": 0.08,
      "passed": true,
      "timed_out": false,
      "stdout": ".ai/runs/project-initialize/verification/05_verify_attempt1_git-diff-check.out.txt",
      "stderr": ".ai/runs/project-initialize/verification/05_verify_attempt1_git-diff-check.err.txt"
    }
  ],
  "failed_commands": []
}
